[
	{ "s": "Д", "p": [11] },
	{ "s": "ДАЁТ", "p": [31] },
	{ "s": "ДАВАЙТЕ", "p": [51] },
	{ "s": "ДАЛЕЕ", "p": [51, 12] },
	{ "s": "ДАЛЬНЕЙШЕМ", "p": [4] },
	{ "s": "ДАННАЯ", "p": [45] },
	{ "s": "ДАННОГО", "p": [45, 11, 10] },
	{ "s": "ДАННОЕ", "p": [45] },
	{ "s": "ДАННОЙ", "p": [45] },
	{ "s": "ДАННОМУ", "p": [31] },
	{ "s": "ДАННЫЕ", "p": [62, 11, 51, 46, 7, 6, 4] },
	{ "s": "ДАННЫЕ.ВИДОБРАЗОВАНИЯ", "p": [62] },
	{ "s": "ДАННЫЕ.НАИМЕНОВАНИЕ", "p": [62] },
	{ "s": "ДАННЫЕПООБУЧАЮЩЕМУСЯ", "p": [20] },
	{ "s": "ДАННЫЕПООБУЧАЮЩЕМУСЯ.ВСТАВИТЬ(КОЛОНКА.ИМЯ", "p": [20] },
	{ "s": "ДАННЫЕСТРОКИ", "p": [6] },
	{ "s": "ДАННЫЙ", "p": [94, 91, 88, 85, 81, 31] },
	{ "s": "ДАННЫМ", "p": [46] },
	{ "s": "ДАННЫМИ", "p": [94, 62, 57, 91, 88, 85, 81, 78, 75, 72, 70, 64, 54] },
	{ "s": "ДАННЫХ", "p": [83, 82, 31, 7, 62, 1, 4, 18, 17, 8] },
	{ "s": "ДАТА", "p": [62, 81, 64, 57, 21, 4] },
	{ "s": "ДАТА(\"20040331000000", "p": [81] },
	{ "s": "ДАТА(2013,02,01", "p": [57] },
	{ "s": "ДАТА(2013,08,31", "p": [57] },
	{ "s": "ДАТАНАЧАЛА", "p": [21] },
	{ "s": "ДАТАОКОНЧАНИЯ", "p": [21] },
	{ "s": "ДАТЕ", "p": [12] },
	{ "s": "ДАТУ", "p": [81, 85] },
	{ "s": "ДВА", "p": [13] },
	{ "s": "ДВАЖДЫ", "p": [82] },
	{ "s": "ДВИЖЕНИЙ", "p": [85] },
	{ "s": "ДВИЖЕНИЯ", "p": [85] },
	{ "s": "ДВИЖЕНИЯ.ОТБОР.РЕГИСТРАТОР.ЗНАЧЕНИЕ", "p": [85] },
	{ "s": "ДВИЖЕНИЯ.ПРОЧИТАТЬ", "p": [85] },
	{ "s": "ДВУХ", "p": [10, 7] },
	{ "s": "ДВУХМЕРНОГО", "p": [4] },
	{ "s": "ДЕЙСТВИЕМ", "p": [51] },
	{ "s": "ДЕЙСТВИЙ", "p": [10, 51] },
	{ "s": "ДЕЙСТВИЯ", "p": [11, 91] },
	{ "s": "ДЕЛАЕМ", "p": [68] },
	{ "s": "ДЕЛАТЬ", "p": [51] },
	{ "s": "ДЕНИС", "p": [54] },
	{ "s": "ДЕРЕВО", "p": [39] },
	{ "s": "ДЕТАЛЬНО", "p": [51] },
	{ "s": "ДИАГНОСТИКА", "p": [81] },
	{ "s": "ДИСЦИПЛИНА", "p": [7] },
	{ "s": "ДЛФ", "p": [62] },
	{ "s": "ДЛЯ", "p": [81, 57, 54, 91, 85, 64, 94, 78, 88, 75, 70, 72, 10, 31, 7, 51, 15, 68, 62, 45, 37, 18, 17, 11, 42, 6, 82, 46, 13, 4, 98, 97, 96, 93, 90, 69, 55, 47, 44, 41, 40, 39, 38, 36, 35, 32, 30, 29, 25, 24, 23, 20, 14, 12, 9, 5] },
	{ "s": "ДЛЯКАЖДОГО", "p": [31] },
	{ "s": "ДОБАВИВ", "p": [31] },
	{ "s": "ДОБАВИМ", "p": [4] },
	{ "s": "ДОБАВИТЬ", "p": [31, 27, 21, 4, 81, 48, 37, 19, 8, 7, 64, 62, 57, 17, 68, 49, 38, 28, 23, 22, 18, 14, 10, 9] },
	{ "s": "ДОБАВЛЕНА", "p": [81, 31] },
	{ "s": "ДОБАВЛЕНИЕ", "p": [31, 4] },
	{ "s": "ДОБАВЛЕНИИ", "p": [68, 45, 31] },
	{ "s": "ДОБАВЛЕНИЯ", "p": [81, 45, 33] },
	{ "s": "ДОБАВЛЕННОЙ", "p": [45] },
	{ "s": "ДОБАВЛЕНЫ", "p": [81, 6] },
	{ "s": "ДОБАВЛЯЕМ", "p": [51] },
	{ "s": "ДОБАВЛЯЕМАЯ", "p": [10] },
	{ "s": "ДОБАВЛЯЕМОГО", "p": [28, 27] },
	{ "s": "ДОБАВЛЯЕМЫХ", "p": [10] },
	{ "s": "ДОБАВЛЯЕТ", "p": [27] },
	{ "s": "ДОБАВЛЯЕТСЯ", "p": [7] },
	{ "s": "ДОКУМЕНТ", "p": [64, 44] },
	{ "s": "ДОКУМЕНТА", "p": [46, 67, 66, 65, 64, 85, 57, 45] },
	{ "s": "ДОКУМЕНТАМ", "p": [51] },
	{ "s": "ДОКУМЕНТАМ-РЕГИСТРАТОРАМ", "p": [51] },
	{ "s": "ДОКУМЕНТАМИ", "p": [64] },
	{ "s": "ДОКУМЕНТАХ", "p": [64] },
	{ "s": "ДОКУМЕНТВЫБОРКА", "p": [64] },
	{ "s": "ДОКУМЕНТЕ", "p": [62, 44] },
	{ "s": "ДОКУМЕНТМЕНЕДЖЕР", "p": [64] },
	{ "s": "ДОКУМЕНТОБЪЕКТ", "p": [64] },
	{ "s": "ДОКУМЕНТОВ", "p": [46, 64] },
	{ "s": "ДОКУМЕНТССЫЛКА", "p": [64] },
	{ "s": "ДОКУМЕНТЫ", "p": [64, 85, 63] },
	{ "s": "ДОКУМЕНТЫ.ОКАЗАНИЕУСЛУГИ.НАЙТИПОНОМЕРУ(13).ПОЛУЧИТЬОБЪЕКТ", "p": [64] },
	{ "s": "ДОКУМЕНТЫ.ПРИХОДНАЯНАКЛАДНАЯ.ВЫБРАТЬ", "p": [64] },
	{ "s": "ДОКУМЕНТЫ.ПРИХОДНАЯНАКЛАДНАЯ.ВЫБРАТЬ(НАЧАЛОМЕСЯЦА(ТЕКУЩАЯДАТА", "p": [64] },
	{ "s": "ДОКУМЕНТЫ.ПРИХОДНАЯНАКЛАДНАЯ.НАЙТИПОНОМЕРУ(\"0000002", "p": [85] },
	{ "s": "ДОКУМЕНТЫ.ПРИХОДНАЯНАКЛАДНАЯ.НАЙТИПОНОМЕРУ(3).ПРОВЕДЕН", "p": [64] },
	{ "s": "ДОКУМЕНТЫ.ПРИХОДНАЯНАКЛАДНАЯ.НАЙТИПОНОМЕРУ(4", "p": [85] },
	{ "s": "ДОКУМЕНТЫ.ПРИХОДНАЯНАКЛАДНАЯ.НАЙТИПОРЕКВИЗИТУ(\"СКЛАД", "p": [64] },
	{ "s": "ДОКУМЕНТЫ.ПРИХОДНАЯНАКЛАДНАЯ.СОЗДАТЬДОКУМЕНТ", "p": [64] },
	{ "s": "ДОКУМЕНТЫ.ТИПВСЕССЫЛКИ().ТИПЫ", "p": [64] },
	{ "s": "ДОКУМЕНТЫ[\"ОКАЗАНИЕУСЛУГИ\"].ПОЛУЧИТЬМАКЕТ(\"ПЕЧАТЬ", "p": [64] },
	{ "s": "ДОКУМЕНТЫМЕНЕДЖЕР", "p": [64] },
	{ "s": "ДОЛЖЕН", "p": [31] },
	{ "s": "ДОЛЖНА", "p": [33] },
	{ "s": "ДОЛЖНОСТЬ", "p": [68, 57] },
	{ "s": "ДОЛЖНЫ", "p": [11] },
	{ "s": "ДОПОЛНИТЕЛЬНАЯ", "p": [49] },
	{ "s": "ДОПОЛНИТЕЛЬНО", "p": [51, 12] },
	{ "s": "ДОПОЛНИТЕЛЬНЫЕСВОЙСТВА", "p": [32] },
	{ "s": "ДОПОЛНИТЕЛЬНЫЙПАРАМЕТР", "p": [34] },
	{ "s": "ДОПОЛНИТЬ", "p": [37] },
	{ "s": "ДОПОЛНИТЬМАССИВ", "p": [37] },
	{ "s": "ДОПОЛНИТЬМАССИВ(МАССИВПРИЕМНИК", "p": [37] },
	{ "s": "ДОПОЛНИТЬСПИСОКИЛИМАССИВЗНАЧЕНИЯМИ", "p": [38] },
	{ "s": "ДОПОЛНИТЬСПИСОКИЛИМАССИВЗНАЧЕНИЯМИ(НАГРУЗКА", "p": [38] },
	{ "s": "ДОПОЛНИТЬСПИСОКИЛИМАССИВЗНАЧЕНИЯМИ(ПРИЕМНИК", "p": [38] },
	{ "s": "ДОПОЛНЯЕТ", "p": [37] },
	{ "s": "ДОПУСТИМАЯДЛИНА", "p": [4] },
	{ "s": "ДОПУСТИМАЯДЛИНА.ПЕРЕМЕННАЯ", "p": [4] },
	{ "s": "ДОПУСТИМЫЕТИПЫ", "p": [4] },
	{ "s": "ДОПУСТИМЫЙЗНАК", "p": [4] },
	{ "s": "ДОПУСТИМЫЙЗНАК.НЕОТРИЦАТЕЛЬНЫЙ", "p": [4] },
	{ "s": "ДОСТАВКА", "p": [6] },
	{ "s": "ДОСТАТОЧНО", "p": [31] },
	{ "s": "ДОСТИГАТЬ", "p": [10] },
	{ "s": "ДОСТУП", "p": [81, 31] },
	{ "s": "ДОСТУПА", "p": [91, 88, 85, 75, 54] },
	{ "s": "ДОСТУПЕН", "p": [31, 28, 16, 7, 6] },
	{ "s": "ДОСТУПНА", "p": [4] },
	{ "s": "ДОСТУПНОСТЬ", "p": [42, 31, 29, 28, 27, 17, 16, 12, 11, 7, 6, 5] },
	{ "s": "ДОСТУПНЫЕВКЛАДКИ", "p": [34] },
	{ "s": "ДРУГИЕ", "p": [96, 31] },
	{ "s": "ДРУГИМИ", "p": [91, 88, 85, 81, 62] },
	{ "s": "ДРУГИХ", "p": [11] },
	{ "s": "ДРУГОЙ", "p": [7] },
	{ "s": "ДРУГУЮ", "p": [9] }
]